handsome/__init__.py
handsome/boy/__init__.py
handsome/boy/message.py
fjl_handsome-0.3.dist-info/METADATA
fjl_handsome-0.3.dist-info/WHEEL
fjl_handsome-0.3.dist-info/top_level.txt
fjl_handsome-0.3.dist-info/RECORD
