Metadata-Version: 2.1
Name: fjl-handsome
Version: 0.3
Summary: 组长：方俊龙，组员：陈彪，叶文龙
Author: 方俊龙
License: UNKNOWN
Platform: UNKNOWN
